automotif/GPU_Executor.py
automotif/__init__.py
automotif/automotif.py
automotifs-1.6.dist-info/LICENSE
automotifs-1.6.dist-info/METADATA
automotifs-1.6.dist-info/WHEEL
automotifs-1.6.dist-info/top_level.txt
automotifs-1.6.dist-info/RECORD
