Metadata-Version: 2.1
Name: automotifs
Version: 1.6
Summary: A wrapper for automatic Motif Detection
Home-page: https://github.com/GiorgioMB/auto_dotmotif/
Author: Giorgio Micaletto
Author-email: giorgio.micaletto@studbocconi.it
Requires-Python: >=3.6
License-File: LICENSE
Requires-Dist: pandas >=1.1.5
Requires-Dist: pylint >=2.6.0
Requires-Dist: numpy >=1.23
Requires-Dist: dotmotif >=0.14.0
Requires-Dist: networkx >=3.2.1
Requires-Dist: matplotlib >=3.8.0
Requires-Dist: seaborn >=0.12.2
